MANIFEST.in
README.md
setup.py
mlstack/__init__.py
mlstack.egg-info/PKG-INFO
mlstack.egg-info/SOURCES.txt
mlstack.egg-info/dependency_links.txt
mlstack.egg-info/top_level.txt
mlstack/analysis/__init__.py
mlstack/analysis/plot_metrics.py
mlstack/feature/__init__.py
mlstack/feature/category_one_hot.py
mlstack/metrics/__init__.py
mlstack/metrics/classification.py
mlstack/model/__init__.py
mlstack/tests/__init__.py
mlstack/tests/analysis/__init__.py
mlstack/tests/analysis/test_plot_metrics.py
mlstack/tests/metrics/__init__.py
mlstack/tests/metrics/test_metrics.py