Metadata-Version: 1.1
Name: mlstack
Version: 1.0b3
Summary: Machine Learning toolkit and algorithms library
Home-page: http://mlstack.org
Author: YintaoXue
Author-email: yintaoxue@gmail.com
License: UNKNOWN
Keywords: MachineLearning AI ML Toolkit
Platform: UNKNOWN
Classifier: Development Status :: 4 - Beta
Classifier: Intended Audience :: Developers
Classifier: Topic :: Scientific/Engineering :: Artificial Intelligence
Classifier: License :: OSI Approved :: BSD License
Classifier: Programming Language :: Python :: 2
Classifier: Programming Language :: Python :: 2.7
Classifier: Programming Language :: Python :: 3
Classifier: Programming Language :: Python :: 3.4
Classifier: Programming Language :: Python :: 3.5
Classifier: Programming Language :: Python :: 3.6
